exar/__init__.py
exar-1.0.0.dist-info/WHEEL
exar-1.0.0.dist-info/METADATA
exar-1.0.0.dist-info/RECORD
