Metadata-Version: 2.3
Name: exar
Version: 1.0.0
Summary: A Unified Experience-Grounded Agentic Reasoning Architecture
Author: Mirko Lenz
Author-email: Mirko Lenz <mirko@mirkolenz.com>
Requires-Python: >=3.12
Project-URL: Changelog, https://github.com/wi2trier/exar/releases
Project-URL: Documentation, https://wi2trier.github.io/exar/
Project-URL: Issues, https://github.com/wi2trier/exar/issues
Project-URL: Repository, https://github.com/wi2trier/exar
